LICENSE.txt
README.md
setup.py
SimpleLinearRegression/LinearRegression.py
SimpleLinearRegression/__init__.py
aya_linear_regression.egg-info/PKG-INFO
aya_linear_regression.egg-info/SOURCES.txt
aya_linear_regression.egg-info/dependency_links.txt
aya_linear_regression.egg-info/top_level.txt