Metadata-Version: 2.1
Name: aya-linear-regression
Version: 0.1.0
Summary: A simple linear regression model from scratch
Home-page: https://github.com/yourusername/aya-linear-regression
Author: aya
Author-email: your.email@example.com
License: MIT
Classifier: Development Status :: 4 - Beta
Classifier: Intended Audience :: Developers
Classifier: License :: OSI Approved :: MIT License
Classifier: Programming Language :: Python :: 3
Requires-Python: >=3.6
License-File: LICENSE.txt
